{
  "metadata": {
    "last_updated": "2026-04-05T14:29:40.203910+00:00",
    "active_cme_id": "CME_2026-04-02T20:46Z"
  },
  "classifications": {
    "CME_2026-04-02T20:46Z": {
      "active": true,
      "classification_window": null,
      "current": {
        "bs_type": "unknown",
        "bs_type_full": "Pre-arrival forecast (ETA 5.5h)",
        "confidence": 20,
        "confidence_trend": "STABLE",
        "locked": false,
        "chirality": "unknown"
      },
      "signatures": {
        "structure_progress_pct": 0,
        "bz_onset_timing": "ETA 5.5h"
      },
      "bz_predictions": {
        "description": "Slow CME (583 km/s). Mild impact expected.",
        "aurora_potential": "WEAK",
        "kp_estimate": "3-5",
        "onset_time": "ETA 5.5h",
        "duration_hours_low": null,
        "duration_hours_high": null,
        "peak_bz_estimate_nT": null
      },
      "phi_events": [],
      "quality_flags": {
        "nosedive_detected": false,
        "reverted": false,
        "boundary_detected": false,
        "expert_review_needed": true
      },
      "notes": [
        "PRE-ARRIVAL FORECAST \u2014 based on CME speed and scoreboard predictions",
        "Bz orientation unknown until CME passes L1 \u2014 confidence reflects this",
        "Classification will sharpen automatically after arrival"
      ]
    },
    "CME_2026-04-01T03:00Z": {
      "active": true,
      "classification_window": null,
      "current": {
        "bs_type": "unknown",
        "bs_type_full": "Classification in progress \u2014 collecting post-arrival L1 data",
        "confidence": 20,
        "confidence_trend": "STABLE",
        "locked": false,
        "chirality": "unknown"
      },
      "signatures": {
        "structure_progress_pct": 0,
        "bz_onset_timing": "ETA arrived"
      },
      "bz_predictions": {
        "description": "Slow CME (554 km/s). Mild impact expected.",
        "aurora_potential": "WEAK",
        "kp_estimate": "3-5",
        "onset_time": "ETA arrived",
        "duration_hours_low": null,
        "duration_hours_high": null,
        "peak_bz_estimate_nT": null
      },
      "phi_events": [],
      "quality_flags": {
        "nosedive_detected": false,
        "reverted": false,
        "boundary_detected": false,
        "expert_review_needed": true
      },
      "notes": [
        "CME ARRIVED \u2014 flux rope classification building",
        "Need ~1.5 hours of post-shock L1 data for Bothmer-Schwenn typing",
        "Confidence will increase as magnetic structure is measured",
        "Only 0.7hr elapsed since arrival - need 1.0hr for classification"
      ]
    }
  }
}